judson/__init__.py
judson-1.0.6.dist-info/LICENSE.txt
judson-1.0.6.dist-info/METADATA
judson-1.0.6.dist-info/WHEEL
judson-1.0.6.dist-info/top_level.txt
judson-1.0.6.dist-info/RECORD
