Metadata-Version: 2.1
Name: judson
Version: 1.0.6
Summary: Howe-style dicts
Author-email: Johannes <johannes-programming@mailfence.com>, Johannes <johannes-programming@posteo.org>
License: The MIT License (MIT)
Project-URL: Documentation, https://pypi.org/project/judson
Project-URL: Download, https://pypi.org/project/judson/#files
Project-URL: Source, https://github.com/johannes-programming/judson
Classifier: License :: OSI Approved :: MIT License
Classifier: Programming Language :: Python
Classifier: Programming Language :: Python :: 3
Classifier: Programming Language :: Python :: 3 :: Only
Requires-Python: >=3.11
License-File: LICENSE.txt
Requires-Dist: howe >=1.0
